inception_audittrail_logger/__init__.py
inception_audittrail_logger/audittrail_elastic.py
inception_audittrail_logger/audittrail_mongo.py
inception_audittrail_logger/format_data.py
inception_audittrail_logger/logging_audittrail.py
inception_audittrail_logger/settings_audittrail.py
inception_audittrail_logger-0.4.2.dist-info/LICENSE
inception_audittrail_logger-0.4.2.dist-info/METADATA
inception_audittrail_logger-0.4.2.dist-info/WHEEL
inception_audittrail_logger-0.4.2.dist-info/top_level.txt
inception_audittrail_logger-0.4.2.dist-info/RECORD
