Metadata-Version: 2.1
Name: inception_audittrail_logger
Version: 0.4.2
Summary: inception_audittrail_logger is a package that allows you to log user activity to a mongodb and elasticsearch
Home-page: https://github.com/KhaduaBloom/inceptionforcepackages/tree/main/PythonPackage/inceptionAuditTrailLogger
Author: KhaduaBloom
Author-email: khaduabloom@gmail.com
Classifier: Programming Language :: Python :: 3
Classifier: License :: OSI Approved :: MIT License
Classifier: Operating System :: OS Independent
Requires-Python: >=3.13.0
License-File: LICENSE
Requires-Dist: graypy==2.1.0
Requires-Dist: psutil==6.1.0
Requires-Dist: fastapi
Requires-Dist: uvicorn
Requires-Dist: pydantic-settings
Requires-Dist: pymongo[srv]
Requires-Dist: elasticsearch==8.17.2
Requires-Dist: opensearch-py
Requires-Dist: requests-aws4auth
Requires-Dist: boto3
Requires-Dist: ua-parser
Requires-Dist: user-agents
Requires-Dist: pyyaml
Requires-Dist: requests
